{
  "content_hash": "1ddb9b1f0c3e2fd278f5108e6bf9fc584b36827db4a449b712df68dafaacaf0a",
  "metadata": {
    "title": "Open the Floodgates: SCOTUS Says South Carolina Can Defund Planned Parenthood. Will Other States Follow?",
    "url": "http://www.democracynow.org/2025/6/27/rebecca_grant_reproductive_health_planned_parenthood",
    "source": "Democracy Now",
    "bias_label": "left",
    "published": "2025-06-27",
    "collected_at": "2025-07-09T20:28:02.748566",
    "id": "5b5e2f9e8beb_1752092890837",
    "author": null,
    "via_google_news": false,
    "via_gdelt": false,
    "via_gov_api": false,
    "extraction_method": "trafilatura",
    "document_id": "5b5e2f9e8beb_1752092890837",
    "stored_at": "2025-07-09T20:28:10.837348"
  },
  "timestamp": "2025-07-09T20:28:10.837726",
  "signature": "Rlyrcac3o8g47nOOurLLP9qtvYdIzEkbDSd7fr/KIOc="
}