{
  "content_hash": "a60da9dbc1beb4f4ef1f36e17af80247db1aedcb6245cbd79cf3ca631fd34034",
  "metadata": {
    "title": "Judge blocks Trump push to cut public school funding over diversity programs - PBS",
    "url": "https://www.pbs.org/newshour/politics/judge-blocks-trump-push-to-cut-public-school-funding-over-diversity-programs",
    "source": "Google News Aggregate",
    "bias_label": "unknown",
    "published": "2025-04-24T17:39:42-04:00",
    "collected_at": "2025-07-09T20:54:06.293882",
    "id": "7d055136b318_1752095299023",
    "author": "Holly Ramer, Associated Press, Collin Binkley",
    "via_google_news": true,
    "via_gdelt": false,
    "via_gov_api": false,
    "extraction_method": "newspaper3k",
    "document_id": "7d055136b318_1752095299023",
    "stored_at": "2025-07-09T21:08:19.023475"
  },
  "timestamp": "2025-07-09T21:08:19.023970",
  "signature": "uCkEGIZS6qM7d16TTg/HG2h26b0M1UZKHg686vgBDkc="
}