{
  "content_hash": "adf00b164e7b376cd405adcae1f89ba019c616ed15f575ab988512e0eccdad38",
  "metadata": {
    "title": "Congress exploiting holy Constitution as weapon to grab power : PM Modi in Haryana Hisar",
    "url": "https://www.thehindu.com/news/national/congress-exploiting-holy-constitution-as-weapon-to-grab-power-pm-modi-in-haryanas-hisar/article69448498.ece",
    "source": "thehindu.com",
    "bias_label": "unknown",
    "published": "2025-04-14",
    "collected_at": "2025-07-09T21:12:42.074487",
    "id": "e3f79cf557dc_1752096356795",
    "author": "Vikas Vasudeva",
    "via_google_news": false,
    "via_gdelt": true,
    "via_gov_api": false,
    "extraction_method": "trafilatura",
    "document_id": "e3f79cf557dc_1752096356795",
    "stored_at": "2025-07-09T21:25:56.795566"
  },
  "timestamp": "2025-07-09T21:25:56.796372",
  "signature": "zy8UwfJA+87RvszqYyk5krYW9LcVDUT0dCN+FsgKD3Y="
}