{
  "title": "As Trump slashed weather agency, his appointees have ties to companies that stand to benefit from privatizing forecasts - PBS",
  "url": "https://www.pbs.org/newshour/politics/as-trump-slashed-weather-agency-his-appointees-have-ties-to-companies-that-stand-to-benefit-from-privatizing-forecasts",
  "source": "Executive Orders Search",
  "bias_label": "aggregate",
  "published": "2025-07-09T13:53:35-04:00",
  "collected_at": "2025-07-09T20:34:18.494798",
  "id": "0fbdc44381df_1752093358414",
  "author": "Brian Slodysko, Associated Press, Michael Biesecker",
  "via_google_news": false,
  "via_gdelt": false,
  "via_gov_api": false,
  "extraction_method": "newspaper3k",
  "document_id": "0fbdc44381df_1752093358414",
  "stored_at": "2025-07-09T20:35:58.414354"
}