{
  "title": "ADJUSTING IMPORTS OF ALUMINUM AND STEEL INTO THE UNITED STATES - The White House (.gov)",
  "url": "https://www.whitehouse.gov/presidential-actions/2025/06/adjusting-imports-of-aluminum-and-steel-into-the-united-states/",
  "source": "Google News Aggregate",
  "bias_label": "unknown",
  "published": "2025-06-03",
  "collected_at": "2025-07-09T20:37:29.421498",
  "id": "3c2896291114_1752095298532",
  "author": null,
  "via_google_news": true,
  "via_gdelt": false,
  "via_gov_api": false,
  "extraction_method": "trafilatura",
  "document_id": "3c2896291114_1752095298532",
  "stored_at": "2025-07-09T21:08:18.532603"
}