{
  "title": "European Intelligence Officials Warn Russian Hybrid War Becoming More Dangerous",
  "url": "https://www.breitbart.com/europe/2025/07/09/european-intelligence-officials-warn-russian-hybrid-war-becoming-more-dangerous/",
  "source": "Breitbart Politics",
  "bias_label": "right",
  "published": "2025-07-09",
  "collected_at": "2025-07-09T20:32:44.839218",
  "id": "3ed3525ccece_1752093169015",
  "author": "Breitbart London",
  "via_google_news": false,
  "via_gdelt": false,
  "via_gov_api": false,
  "extraction_method": "trafilatura",
  "document_id": "3ed3525ccece_1752093169015",
  "stored_at": "2025-07-09T20:32:49.015295"
}