{
  "title": "DIRECTING THE REPEAL OF UNLAWFUL REGULATIONS - The White House (.gov)",
  "url": "https://www.whitehouse.gov/presidential-actions/2025/04/directing-the-repeal-of-unlawful-regulations/",
  "source": "Google News Aggregate",
  "bias_label": "unknown",
  "published": "2025-04-09",
  "collected_at": "2025-07-09T20:42:10.010018",
  "id": "593371947096_1752095298616",
  "author": null,
  "via_google_news": true,
  "via_gdelt": false,
  "via_gov_api": false,
  "extraction_method": "trafilatura",
  "document_id": "593371947096_1752095298616",
  "stored_at": "2025-07-09T21:08:18.617023"
}