{
  "title": "Trump talks tariffs, Russia, Iran at Cabinet meeting; Supreme Court allows mass federal layoffs - NBC News",
  "url": "https://www.nbcnews.com/politics/trump-administration/live-blog/trump-netanyahu-congress-ukraine-iran-gaza-tariffs-live-updates-rcna217064",
  "source": "Google News Aggregate",
  "bias_label": "unknown",
  "published": "2025-07-08",
  "collected_at": "2025-07-09T21:01:12.033682",
  "id": "9a9ab1c1a837_1752095299265",
  "author": "Brennan Leach Brennan Leach is a Desk Assistant",
  "via_google_news": true,
  "via_gdelt": false,
  "via_gov_api": false,
  "extraction_method": "trafilatura",
  "document_id": "9a9ab1c1a837_1752095299265",
  "stored_at": "2025-07-09T21:08:19.265986"
}